{
  "anthem": "Anthem",
  "bible": "Reading",
  "canticle": "Canticle",
  "collect_of_the_day": "Collect of the Day",
  "heading": "Heading",
  "hymn": "Hymn",
  "lectionary-reading": "Lectionary Reading",
  "litany": "Litany",
  "meditation": "Meditation",
  "option": "Option",
  "prayer": "Prayer",
  "preces": "Preces",
  "psalm": "Psalm",
  "psalter": "Lectionary Psalms",
  "refrain": "Refrain",
  "responsive": "Responsive Prayer",
  "rubric": "Rubric",
  "text": "Text",
  "title": "Add a Block",
  "Reading": "Reading",
  "Prayer": "Prayer",
  "Liturgy": "Liturgy",
  "Music": "Music"
}
